swh.perfecthash-1.3.2.dist-info/LICENSE
swh.perfecthash-1.3.2.dist-info/RECORD
swh.perfecthash-1.3.2.dist-info/top_level.txt
swh.perfecthash-1.3.2.dist-info/WHEEL
swh.perfecthash-1.3.2.dist-info/METADATA
swh.perfecthash-1.3.2.dist-info/AUTHORS
swh/perfecthash/__init__.py
swh/perfecthash/hash.h
swh/perfecthash/Makefile
swh/perfecthash/_hash_cffi.abi3.so
swh/perfecthash/test_hash.cpp
swh/perfecthash/hash.c
swh/perfecthash/build.py
swh/perfecthash/py.typed
swh/perfecthash/tests/test_hash.py
swh/perfecthash/tests/__init__.py
swh.perfecthash.libs/libcmph-c86397e2.so.0.0.0
